autogen_agents/__about__.py
autogen_agents/__init__.py
autogen_agents/__main__.py
autogen_agents-0.0.0.dist-info/METADATA
autogen_agents-0.0.0.dist-info/WHEEL
autogen_agents-0.0.0.dist-info/licenses/LICENSE
autogen_agents-0.0.0.dist-info/RECORD
